grading_lib/VERSION
grading_lib/__init__.py
grading_lib/__main__.py
grading_lib/common.py
grading_lib/makefile.py
grading_lib/py.typed
grading_lib/qa.py
grading_lib/repository.py
grading_lib/util.py
grading_lib/cli/__init__.py
grading_lib/cli/dev.py
grading_lib/cli/internal.py
grading_lib/tools/__init__.py
grading_lib/tools/collect_autograding_tests.py
cs3560_grading_lib-0.1.1.dist-info/LICENSE
cs3560_grading_lib-0.1.1.dist-info/METADATA
cs3560_grading_lib-0.1.1.dist-info/WHEEL
cs3560_grading_lib-0.1.1.dist-info/top_level.txt
cs3560_grading_lib-0.1.1.dist-info/RECORD
