Metadata-Version: 2.1
Name: cs3560-grading-lib
Version: 0.1.1
Summary: A common library for the grading scripts.
License: MIT License
Project-URL: Documentation, https://grading-lib.readthedocs.io/en/latest/
Project-URL: Source Code, https://github.com/OU-CS3560/cs3560-grading-lib
Project-URL: Issue Tracker, https://github.com/OU-CS3560/cs3560-grading-lib/issues
Project-URL: Changelog, https://github.com/OU-CS3560/cs3560-grading-lib/blob/main/CHANGELOG.md
Classifier: Programming Language :: Python :: 3.10
Classifier: Development Status :: 3 - Alpha
Classifier: Intended Audience :: Education
Classifier: License :: OSI Approved :: MIT License
Classifier: Natural Language :: English
Classifier: Topic :: Education :: Testing
Requires-Python: >=3.10
License-File: LICENSE
Requires-Dist: click
Requires-Dist: tomli
Requires-Dist: GitPython
Requires-Dist: typing-extensions <5,>=4.12
Requires-Dist: importlib-metadata ; python_version >= "3.10"
Provides-Extra: dev
Requires-Dist: pytest ; extra == 'dev'
Requires-Dist: pytest-cov ; extra == 'dev'
Requires-Dist: mypy ; extra == 'dev'
Requires-Dist: ruff ; extra == 'dev'
Requires-Dist: tox ; extra == 'dev'
